voicebox/__init__.py
voicebox/__main__.py
voicebox/audio.py
voicebox/ssml.py
voicebox/types.py
voicebox/utils.py
voicebox/version.py
voicebox/effects/__init__.py
voicebox/effects/chain.py
voicebox/effects/dc_offset.py
voicebox/effects/effect.py
voicebox/effects/eq.py
voicebox/effects/flanger.py
voicebox/effects/glitch.py
voicebox/effects/normalize.py
voicebox/effects/pedalboard.py
voicebox/effects/ring_mod.py
voicebox/effects/tail.py
voicebox/effects/utils.py
voicebox/effects/vocoder.py
voicebox/examples/__init__.py
voicebox/examples/battle_droid.py
voicebox/examples/demo.py
voicebox/examples/glados.py
voicebox/examples/halo_spark.py
voicebox/sinks/__init__.py
voicebox/sinks/distributor.py
voicebox/sinks/sink.py
voicebox/sinks/sounddevice.py
voicebox/sinks/wavefile.py
voicebox/tts/__init__.py
voicebox/tts/amazonpolly.py
voicebox/tts/cache.py
voicebox/tts/elevenlabs.py
voicebox/tts/espeakng.py
voicebox/tts/googlecloudtts.py
voicebox/tts/gtts.py
voicebox/tts/parlertts.py
voicebox/tts/picotts.py
voicebox/tts/pyttsx3.py
voicebox/tts/tts.py
voicebox/tts/utils.py
voicebox/voiceboxes/__init__.py
voicebox/voiceboxes/base.py
voicebox/voiceboxes/parallel.py
voicebox/voiceboxes/queue.py
voicebox/voiceboxes/simple.py
voicebox/voiceboxes/splitter.py
voicebox_tts-0.0.13.dist-info/LICENSE
voicebox_tts-0.0.13.dist-info/METADATA
voicebox_tts-0.0.13.dist-info/WHEEL
voicebox_tts-0.0.13.dist-info/top_level.txt
voicebox_tts-0.0.13.dist-info/RECORD
