Metadata-Version: 2.2
Name: voicebox-tts
Version: 0.0.13
Summary: Python text-to-speech library with built-in voice effects and support for multiple TTS engines.
Author-email: Austin Bowen <austin.bowen.314@gmail.com>
License: MIT License
Project-URL: Homepage, https://github.com/austin-bowen/voicebox
Project-URL: Issues, https://github.com/austin-bowen/voicebox/issues
Classifier: License :: OSI Approved :: MIT License
Classifier: Operating System :: OS Independent
Classifier: Programming Language :: Python
Classifier: Programming Language :: Python :: 3
Classifier: Programming Language :: Python :: 3.9
Classifier: Programming Language :: Python :: 3.10
Classifier: Programming Language :: Python :: 3.11
Classifier: Programming Language :: Python :: 3.12
Classifier: Programming Language :: Python :: 3.13
Classifier: Programming Language :: Python :: 3 :: Only
Requires-Python: >=3.9
License-File: LICENSE
Requires-Dist: audioread
Requires-Dist: cachetools
Requires-Dist: nltk
Requires-Dist: numpy
Requires-Dist: pedalboard
Requires-Dist: scipy
Requires-Dist: sounddevice
Provides-Extra: all
Requires-Dist: voicebox-tts[dev]; extra == "all"
Requires-Dist: voicebox-tts[docs]; extra == "all"
Requires-Dist: voicebox-tts[test]; extra == "all"
Requires-Dist: voicebox-tts[amazon-polly]; extra == "all"
Requires-Dist: voicebox-tts[elevenlabs]; extra == "all"
Requires-Dist: voicebox-tts[google-cloud-tts]; extra == "all"
Requires-Dist: voicebox-tts[gtts]; extra == "all"
Requires-Dist: voicebox-tts[pyttsx3]; extra == "all"
Provides-Extra: dev
Requires-Dist: build; extra == "dev"
Requires-Dist: invoke; extra == "dev"
Requires-Dist: twine; extra == "dev"
Provides-Extra: docs
Requires-Dist: myst-parser; extra == "docs"
Requires-Dist: sphinx; extra == "docs"
Requires-Dist: sphinx-rtd-theme; extra == "docs"
Provides-Extra: test
Requires-Dist: coverage; extra == "test"
Requires-Dist: parameterized; extra == "test"
Requires-Dist: pytest; extra == "test"
Provides-Extra: amazon-polly
Requires-Dist: boto3; extra == "amazon-polly"
Requires-Dist: boto3-stubs; extra == "amazon-polly"
Requires-Dist: boto3-stubs[polly]; extra == "amazon-polly"
Provides-Extra: elevenlabs
Requires-Dist: elevenlabs; extra == "elevenlabs"
Provides-Extra: google-cloud-tts
Requires-Dist: google-cloud-texttospeech; extra == "google-cloud-tts"
Provides-Extra: gtts
Requires-Dist: gTTS; extra == "gtts"
Provides-Extra: pyttsx3
Requires-Dist: pyttsx3; extra == "pyttsx3"
